cloudshell/__init__.py
cloudshell/cp/__init__.py
cloudshell/cp/docker/__init__.py
cloudshell/cp/docker/docker_shell.py
cloudshell/cp/docker/common/__init__.py
cloudshell/cp/docker/common/deploy_data_holder.py
cloudshell/cp/docker/domain/__init__.py
cloudshell/cp/docker/domain/context/__init__.py
cloudshell/cp/docker/domain/context/api_session_context.py
cloudshell/cp/docker/domain/context/resource_model_context.py
cloudshell/cp/docker/domain/context/shell_context.py
cloudshell/cp/docker/domain/services/__init__.py
cloudshell/cp/docker/domain/services/parsers/__init__.py
cloudshell/cp/docker/domain/services/parsers/command_results_parser.py
cloudshell/cp/docker/domain/services/parsers/models_parser.py
cloudshell/cp/docker/domain/services/session_providers/__init__.py
cloudshell/cp/docker/domain/services/session_providers/session_provider.py
cloudshell/cp/docker/models/__init__.py
cloudshell/cp/docker/models/clients.py
cloudshell/cp/docker/models/cloud_provider_resource_model.py
cloudshell/cp/docker/models/deploy_docker_container_resource_model.py
cloudshell/cp/docker/models/deploy_result.py
cloudshell/cp/docker/models/prepare_connectivity_action_result.py
cloudshell_cp_docker-0.1.54.dist-info/DESCRIPTION.rst
cloudshell_cp_docker-0.1.54.dist-info/METADATA
cloudshell_cp_docker-0.1.54.dist-info/RECORD
cloudshell_cp_docker-0.1.54.dist-info/WHEEL
cloudshell_cp_docker-0.1.54.dist-info/metadata.json
cloudshell_cp_docker-0.1.54.dist-info/top_level.txt
